trainer_pytorch/__init__.py
trainer_pytorch/trainer_pytorch.py
trainer_pytorch-0.0.2.dist-info/licenses/LICENSE
trainer_pytorch-0.0.2.dist-info/METADATA
trainer_pytorch-0.0.2.dist-info/WHEEL
trainer_pytorch-0.0.2.dist-info/top_level.txt
trainer_pytorch-0.0.2.dist-info/RECORD
