Metadata-Version: 2.4
Name: trainer-pytorch
Version: 0.0.2
Summary: Generic Pytorch Trainer
Home-page: https://github.com/pacocp/trainer_pytorch
Author: Francisco Carrillo Pérez
Author-email: Francisco Carrillo Pérez <carrilloperezfrancisco@gmail.com>
License: MIT License
Project-URL: Homepage, https://pypi.org/project/trainer-pytorch/
Project-URL: Repository, https://github.com/pacocp/trainer-pytorch
Keywords: artificial intelligence,deep learning,transformers,flow matching,autonomous driving
Classifier: Development Status :: 4 - Beta
Classifier: Intended Audience :: Developers
Classifier: Topic :: Scientific/Engineering :: Artificial Intelligence
Classifier: License :: OSI Approved :: MIT License
Classifier: Programming Language :: Python :: 3.9
Requires-Python: >=3.9
License-File: LICENSE
Requires-Dist: torch>=2.2
Requires-Dist: wandb>=0.20.1
Requires-Dist: accelerate>=0.10.0
Requires-Dist: pytest>=8.4.1
Provides-Extra: examples
Provides-Extra: test
Requires-Dist: pytest; extra == "test"
Dynamic: author
Dynamic: home-page
Dynamic: license-file
